congress_crawler/__init__.py
congress_crawler/adler_wilkerson_bills.py
congress_crawler/amendment_info.py
congress_crawler/bill_info.py
congress_crawler/bills.py
congress_crawler/committee_meetings.py
congress_crawler/govinfo.py
congress_crawler/nomination_info.py
congress_crawler/nominations.py
congress_crawler/statutes.py
congress_crawler/upcoming_house_floor.py
congress_crawler/utils.py
congress_crawler/vote_info.py
congress_crawler/votes.py
congress_crawler/voteview.py
congress_crawler/voteview_codedoptions.csv
contrib/__init__.py
contrib/beanstalkd.py
congress_crawler-0.0.2.dist-info/LICENSE
congress_crawler-0.0.2.dist-info/METADATA
congress_crawler-0.0.2.dist-info/WHEEL
congress_crawler-0.0.2.dist-info/top_level.txt
congress_crawler-0.0.2.dist-info/RECORD
