Metadata-Version: 2.1
Name: congress-crawler
Version: 0.0.2
Summary: Gathers data on the U.S. Congress.
Home-page: https://github.com/Hear-Ye/congress
Author: Andrew Chen Wang
Author-email: acwangpython@gmail.com
License: CC0
Platform: UNKNOWN
Classifier: Development Status :: 5 - Production/Stable
Classifier: Framework :: Django
Classifier: Intended Audience :: Developers
Classifier: License :: CC0 1.0 Universal (CC0 1.0) Public Domain Dedication
Classifier: Operating System :: OS Independent
Classifier: Programming Language :: Python :: 3
Classifier: Programming Language :: Python :: 3.6
Classifier: Programming Language :: Python :: 3.7
Classifier: Programming Language :: Python :: 3.8
Classifier: Programming Language :: Python :: 3.9
Classifier: Topic :: Internet :: WWW/HTTP
Requires-Dist: pyyaml
Requires-Dist: python-dateutil
Requires-Dist: lxml (>=2.2)
Requires-Dist: pytz
Requires-Dist: cssselect
Requires-Dist: scrapelib
Requires-Dist: mechanize
Requires-Dist: BeautifulSoup4
Requires-Dist: xmltodict
Requires-Dist: rtyaml
Requires-Dist: requests
